rsp/__init__.py
rsp/drl/__init__.py
rsp/drl/agent/__init__.py
rsp/drl/agent/agent.py
rsp/drl/environment/__init__.py
rsp/drl/environment/environment.py
rsp/drl/environment/image/robot-kuka-base.png
rsp/drl/environment/image/robot-kuka-link1.png
rsp/drl/environment/image/robot-kuka-link2.png
rsp/drl/run/__init__.py
rsp/drl/run/run.py
rsp_drl-0.0.38.dist-info/LICENSE
rsp_drl-0.0.38.dist-info/METADATA
rsp_drl-0.0.38.dist-info/WHEEL
rsp_drl-0.0.38.dist-info/top_level.txt
rsp_drl-0.0.38.dist-info/RECORD
