Metadata-Version: 2.1
Name: rsp-drl
Version: 0.0.38
Summary: Some basic functionalities
Home-page: https://github.com/SchulzR97/rsp-drl
Author: Robert Schulz
Author-email: schulzr256@gmail.com
License: MIT
Keywords: python,Reinforement learning,Deep Reinforcement Learning
Classifier: Development Status :: 3 - Alpha
Classifier: Intended Audience :: Education
Classifier: Programming Language :: Python :: 2
Classifier: Programming Language :: Python :: 3
Classifier: Operating System :: MacOS :: MacOS X
Classifier: Operating System :: Microsoft :: Windows
Classifier: Operating System :: POSIX :: Linux
License-File: LICENSE
Requires-Dist: torch
Requires-Dist: torchvision
Requires-Dist: torchaudio
Requires-Dist: rsp-common
Requires-Dist: numpy
Requires-Dist: opencv-python
Requires-Dist: gym
Requires-Dist: matplotlib
Requires-Dist: rsp-ml
